pyspiral-0.9.19.dist-info/METADATA
pyspiral-0.9.19.dist-info/WHEEL
pyspiral-0.9.19.dist-info/entry_points.txt
spiral/__init__.py
spiral/_lib.abi3.so
spiral/adbc.py
spiral/api/__init__.py
spiral/api/admin.py
spiral/api/client.py
spiral/api/filesystems.py
spiral/api/key_space_indexes.py
spiral/api/organizations.py
spiral/api/projects.py
spiral/api/tables.py
spiral/api/telemetry.py
spiral/api/text_indexes.py
spiral/api/types.py
spiral/api/workers.py
spiral/api/workloads.py
spiral/arrow_.py
spiral/cli/__init__.py
spiral/cli/__main__.py
spiral/cli/admin.py
spiral/cli/app.py
spiral/cli/chooser.py
spiral/cli/console.py
spiral/cli/fs.py
spiral/cli/iceberg.py
spiral/cli/key_spaces.py
spiral/cli/login.py
spiral/cli/orgs.py
spiral/cli/printer.py
spiral/cli/projects.py
spiral/cli/state.py
spiral/cli/tables.py
spiral/cli/telemetry.py
spiral/cli/text.py
spiral/cli/tools.py
spiral/cli/transactions.py
spiral/cli/types_.py
spiral/cli/workloads.py
spiral/client.py
spiral/core/__init__.pyi
spiral/core/_tools/__init__.pyi
spiral/core/authn/__init__.pyi
spiral/core/client/__init__.pyi
spiral/core/config/__init__.pyi
spiral/core/expr/__init__.pyi
spiral/core/expr/images/__init__.pyi
spiral/core/expr/list_/__init__.pyi
spiral/core/expr/pushdown/__init__.pyi
spiral/core/expr/refs/__init__.pyi
spiral/core/expr/s3/__init__.pyi
spiral/core/expr/str_/__init__.pyi
spiral/core/expr/struct_/__init__.pyi
spiral/core/expr/text/__init__.pyi
spiral/core/expr/udf/__init__.pyi
spiral/core/expr/video/__init__.pyi
spiral/core/table/__init__.pyi
spiral/core/table/manifests/__init__.pyi
spiral/core/table/metastore/__init__.pyi
spiral/core/table/spec/__init__.pyi
spiral/dataloader.py
spiral/dataset.py
spiral/datetime_.py
spiral/debug/__init__.py
spiral/debug/manifests.py
spiral/debug/metrics.py
spiral/debug/scan.py
spiral/demo.py
spiral/enrichment.py
spiral/expressions/__init__.py
spiral/expressions/base.py
spiral/expressions/file.py
spiral/expressions/http.py
spiral/expressions/list_.py
spiral/expressions/pushdown.py
spiral/expressions/s3.py
spiral/expressions/str_.py
spiral/expressions/struct.py
pyspiral-0.9.19.dist-info/RECORD
