Metadata-Version: 2.4
Name: pyspiral
Version: 0.9.19
Classifier: Intended Audience :: Science/Research
Classifier: Operating System :: OS Independent
Classifier: Programming Language :: Python
Classifier: Programming Language :: Python :: 3
Classifier: Programming Language :: Python :: 3 :: Only
Classifier: Programming Language :: Python :: 3.11
Classifier: Programming Language :: Python :: 3.12
Classifier: Programming Language :: Python :: 3.13
Classifier: Programming Language :: Python :: 3.14
Classifier: Programming Language :: Rust
Classifier: License :: Other/Proprietary License
Requires-Dist: betterproto2>=0.9.0
Requires-Dist: google-re2>=1.1.20240702
Requires-Dist: grpclib>=0.4.7
Requires-Dist: hishel>=0.0.30
Requires-Dist: httpx>=0.27.0
Requires-Dist: nanoid>=2.0.0
Requires-Dist: pyarrow>=21.0.0
Requires-Dist: pydantic-settings>=2.3.4
Requires-Dist: pydantic[email]>=2.12.4,<2.13
Requires-Dist: pyjwt[crypto]>=2.9.0
Requires-Dist: pyperclip>=1.9.0
Requires-Dist: questionary>=2.0.1
Requires-Dist: sqlglot[rs]>=25.25.1
Requires-Dist: tqdm>=4.66.5
Requires-Dist: typer>=0.16
Requires-Dist: xxhash>=3.4.1
Requires-Dist: zstandard>=0.23.0
Requires-Dist: orjson>=3.10.0
Requires-Dist: dask>=2025.10.0 ; extra == 'dask'
Requires-Dist: distributed>=2025.10.0 ; extra == 'dask'
Requires-Dist: duckdb>=1.3.2 ; extra == 'duckdb'
Requires-Dist: datasets>=4.3.0 ; extra == 'huggingface'
Requires-Dist: pyiceberg[s3fs]>=0.9.1 ; extra == 'iceberg'
Requires-Dist: polars>=1.31.0 ; extra == 'polars'
Requires-Dist: ray[data]>=2.0.0 ; python_full_version < '3.14' and extra == 'ray'
Requires-Dist: mosaicml-streaming>=0.13.0 ; extra == 'streaming'
Requires-Dist: vortex-data>=0.52.1 ; extra == 'streaming'
Provides-Extra: dask
Provides-Extra: duckdb
Provides-Extra: huggingface
Provides-Extra: iceberg
Provides-Extra: polars
Provides-Extra: ray
Provides-Extra: streaming
Summary: Python client for Spiral.
Home-Page: https://spiraldb.com
Author-email: SpiralDB <hello@spiraldb.com>
License: Proprietary License
Requires-Python: >=3.11
